<?xml version="1.0" encoding="utf-8"?>
<ctatt>
	<tmst>20130212 13:50:59</tmst>
	<errCd>0</errCd>
	<errNm />
	<eta>
		<staId>40380</staId>
		<stpId>30074</stpId>
		<staNm>Clark/Lake</staNm>
		<stpDe>Service at Inner Loop platform</stpDe>
		<rn>718</rn>
		<rt>Org</rt>
		<destSt>30182</destSt>
		<destNm>Midway</destNm>
		<trDr>5</trDr>
		<prdt>20130212 13:49:54</prdt>
		<arrT>20130212 13:50:54</arrT>
		<isApp>1</isApp>
		<isSch>0</isSch>
		<isDly>0</isDly>
		<isFlt>0</isFlt>
		<flags />
	</eta>
	<eta>
		<staId>40380</staId>
		<stpId>30374</stpId>
		<staNm>Clark/Lake</staNm>
		<stpDe>Subway service toward Forest Park</stpDe>
		<rn>108</rn>
		<rt>Blue</rt>
		<destSt>0</destSt>
		<destNm>Forest Park</destNm>
		<trDr>5</trDr>
		<prdt>20130212 13:50:12</prdt>
		<arrT>20130212 13:51:12</arrT>
		<isApp>1</isApp>
		<isSch>0</isSch>
		<isDly>0</isDly>
		<isFlt>0</isFlt>
		<flags />
	</eta>
	<eta>
		<staId>40380</staId>
		<stpId>30075</stpId>
		<staNm>Clark/Lake</staNm>
		<stpDe>Service at Outer Loop platform</stpDe>
		<rn>415</rn>
		<rt>Brn</rt>
		<destSt>30249</destSt>
		<destNm>Kimball</destNm>
		<trDr>1</trDr>
		<prdt>20130212 13:50:15</prdt>
		<arrT>20130212 13:53:15</arrT>
		<isApp>0</isApp>
		<isSch>0</isSch>
		<isDly>0</isDly>
		<isFlt>0</isFlt>
		<flags />
	</eta>
	<eta>
		<staId>40380</staId>
		<stpId>30074</stpId>
		<staNm>Clark/Lake</staNm>
		<stpDe>Service at Inner Loop platform</stpDe>
		<rn>014</rn>
		<rt>G</rt>
		<destSt>30057</destSt>
		<destNm>Ashland/63rd</destNm>
		<trDr>5</trDr>
		<prdt>20130212 13:50:05</prdt>
		<arrT>20130212 13:54:05</arrT>
		<isApp>0</isApp>
		<isSch>0</isSch>
		<isDly>0</isDly>
		<isFlt>0</isFlt>
		<flags />
	</eta>
	<eta>
		<staId>40380</staId>
		<stpId>30075</stpId>
		<staNm>Clark/Lake</staNm>
		<stpDe>Service at Outer Loop platform</stpDe>
		<rn>002</rn>
		<rt>G</rt>
		<destSt>30004</destSt>
		<destNm>Harlem/Lake</destNm>
		<trDr>1</trDr>
		<prdt>20130212 13:50:15</prdt>
		<arrT>20130212 13:54:15</arrT>
		<isApp>0</isApp>
		<isSch>0</isSch>
		<isDly>0</isDly>
		<isFlt>0</isFlt>
		<flags />
	</eta>
	<eta>
		<staId>40380</staId>
		<stpId>30375</stpId>
		<staNm>Clark/Lake</staNm>
		<stpDe>Subway service toward O'Hare</stpDe>
		<rn>114</rn>
		<rt>Blue</rt>
		<destSt>30171</destSt>
		<destNm>O'Hare</destNm>
		<trDr>1</trDr>
		<prdt>20130212 13:50:11</prdt>
		<arrT>20130212 13:55:11</arrT>
		<isApp>0</isApp>
		<isSch>0</isSch>
		<isDly>0</isDly>
		<isFlt>0</isFlt>
		<flags />
	</eta>
	<eta>
		<staId>40380</staId>
		<stpId>30074</stpId>
		<staNm>Clark/Lake</staNm>
		<stpDe>Service at Inner Loop platform</stpDe>
		<rn>714</rn>
		<rt>Org</rt>
		<destSt>30182</destSt>
		<destNm>Midway</destNm>
		<trDr>5</trDr>
		<prdt>20130212 13:50:10</prdt>
		<arrT>20130212 13:55:10</arrT>
		<isApp>0</isApp>
		<isSch>0</isSch>
		<isDly>0</isDly>
		<isFlt>0</isFlt>
		<flags />
	</eta>
	<eta>
		<staId>40380</staId>
		<stpId>30374</stpId>
		<staNm>Clark/Lake</staNm>
		<stpDe>Subway service toward Forest Park</stpDe>
		<rn>126</rn>
		<rt>Blue</rt>
		<destSt>0</destSt>
		<destNm>Forest Park</destNm>
		<trDr>5</trDr>
		<prdt>20130212 13:50:05</prdt>
		<arrT>20130212 13:57:05</arrT>
		<isApp>0</isApp>
		<isSch>0</isSch>
		<isDly>0</isDly>
		<isFlt>0</isFlt>
		<flags />
	</eta>
	<eta>
		<staId>40380</staId>
		<stpId>30074</stpId>
		<staNm>Clark/Lake</staNm>
		<stpDe>Service at Inner Loop platform</stpDe>
		<rn>305</rn>
		<rt>Pink</rt>
		<destSt>0</destSt>
		<destNm>54th/Cermak</destNm>
		<trDr>5</trDr>
		<prdt>20130212 13:50:13</prdt>
		<arrT>20130212 14:00:13</arrT>
		<isApp>0</isApp>
		<isSch>0</isSch>
		<isDly>0</isDly>
		<isFlt>0</isFlt>
		<flags />
	</eta>
	<eta>
		<staId>40380</staId>
		<stpId>30374</stpId>
		<staNm>Clark/Lake</staNm>
		<stpDe>Subway service toward Forest Park</stpDe>
		<rn>116</rn>
		<rt>Blue</rt>
		<destSt>0</destSt>
		<destNm>Forest Park</destNm>
		<trDr>5</trDr>
		<prdt>20130212 13:50:10</prdt>
		<arrT>20130212 14:01:10</arrT>
		<isApp>0</isApp>
		<isSch>0</isSch>
		<isDly>0</isDly>
		<isFlt>0</isFlt>
		<flags />
	</eta>
	<eta>
		<staId>40380</staId>
		<stpId>30074</stpId>
		<staNm>Clark/Lake</staNm>
		<stpDe>Service at Inner Loop platform</stpDe>
		<rn>710</rn>
		<rt>Org</rt>
		<destSt>30182</destSt>
		<destNm>Midway</destNm>
		<trDr>5</trDr>
		<prdt>20130212 13:50:09</prdt>
		<arrT>20130212 14:02:09</arrT>
		<isApp>0</isApp>
		<isSch>0</isSch>
		<isDly>0</isDly>
		<isFlt>0</isFlt>
		<flags />
	</eta>
	<eta>
		<staId>40380</staId>
		<stpId>30074</stpId>
		<staNm>Clark/Lake</staNm>
		<stpDe>Service at Inner Loop platform</stpDe>
		<rn>015</rn>
		<rt>G</rt>
		<destSt>30139</destSt>
		<destNm>Cottage Grove</destNm>
		<trDr>5</trDr>
		<prdt>20130212 13:49:51</prdt>
		<arrT>20130212 14:02:51</arrT>
		<isApp>0</isApp>
		<isSch>0</isSch>
		<isDly>0</isDly>
		<isFlt>0</isFlt>
		<flags />
	</eta>
	<eta>
		<staId>40380</staId>
		<stpId>30375</stpId>
		<staNm>Clark/Lake</staNm>
		<stpDe>Subway service toward O'Hare</stpDe>
		<rn>115</rn>
		<rt>Blue</rt>
		<destSt>30171</destSt>
		<destNm>O'Hare</destNm>
		<trDr>1</trDr>
		<prdt>20130212 13:49:42</prdt>
		<arrT>20130212 14:04:42</arrT>
		<isApp>0</isApp>
		<isSch>0</isSch>
		<isDly>0</isDly>
		<isFlt>0</isFlt>
		<flags />
	</eta>
	<eta>
		<staId>40380</staId>
		<stpId>30075</stpId>
		<staNm>Clark/Lake</staNm>
		<stpDe>Service at Outer Loop platform</stpDe>
		<rn>422</rn>
		<rt>Brn</rt>
		<destSt>30249</destSt>
		<destNm>Kimball</destNm>
		<trDr>1</trDr>
		<prdt>20130212 13:49:21</prdt>
		<arrT>20130212 14:05:21</arrT>
		<isApp>0</isApp>
		<isSch>0</isSch>
		<isDly>0</isDly>
		<isFlt>0</isFlt>
		<flags />
	</eta>
	<eta>
		<staId>40380</staId>
		<stpId>30374</stpId>
		<staNm>Clark/Lake</staNm>
		<stpDe>Subway service toward Forest Park</stpDe>
		<rn>127</rn>
		<rt>Blue</rt>
		<destSt>0</destSt>
		<destNm>Forest Park</destNm>
		<trDr>5</trDr>
		<prdt>20130212 13:50:12</prdt>
		<arrT>20130212 14:08:12</arrT>
		<isApp>0</isApp>
		<isSch>0</isSch>
		<isDly>0</isDly>
		<isFlt>0</isFlt>
		<flags />
	</eta>
	<eta>
		<staId>40380</staId>
		<stpId>30075</stpId>
		<staNm>Clark/Lake</staNm>
		<stpDe>Service at Outer Loop platform</stpDe>
		<rn>613</rn>
		<rt>G</rt>
		<destSt>30004</destSt>
		<destNm>Harlem/Lake</destNm>
		<trDr>1</trDr>
		<prdt>20130212 13:49:41</prdt>
		<arrT>20130212 14:07:41</arrT>
		<isApp>0</isApp>
		<isSch>0</isSch>
		<isDly>0</isDly>
		<isFlt>0</isFlt>
		<flags />
	</eta>
	<eta>
		<staId>40380</staId>
		<stpId>30075</stpId>
		<staNm>Clark/Lake</staNm>
		<stpDe>Service at Outer Loop platform</stpDe>
		<rn>405</rn>
		<rt>Brn</rt>
		<destSt>30249</destSt>
		<destNm>Kimball</destNm>
		<trDr>1</trDr>
		<prdt>20130212 13:49:20</prdt>
		<arrT>20130212 14:08:20</arrT>
		<isApp>0</isApp>
		<isSch>0</isSch>
		<isDly>0</isDly>
		<isFlt>0</isFlt>
		<flags />
	</eta>
	<eta>
		<staId>40380</staId>
		<stpId>30074</stpId>
		<staNm>Clark/Lake</staNm>
		<stpDe>Service at Inner Loop platform</stpDe>
		<rn>307</rn>
		<rt>Pink</rt>
		<destSt>0</destSt>
		<destNm>54th/Cermak</destNm>
		<trDr>5</trDr>
		<prdt>20130212 13:49:47</prdt>
		<arrT>20130212 14:08:47</arrT>
		<isApp>0</isApp>
		<isSch>0</isSch>
		<isDly>0</isDly>
		<isFlt>0</isFlt>
		<flags />
	</eta>
</ctatt>